dabpumps/__about__.py
dabpumps/__init__.py
dabpumps/auth.py
dabpumps/const.py
dabpumps/dconnect.py
dabpumps/exceptions.py
dabpumps/installation.py
dabpumps/pump.py
dabpumps-0.1.0.dist-info/METADATA
dabpumps-0.1.0.dist-info/WHEEL
dabpumps-0.1.0.dist-info/licenses/LICENSE.txt
dabpumps-0.1.0.dist-info/RECORD
